iva_order_selection/__init__.py
iva_order_selection/order_selection_iva.py
iva_order_selection-0.0.2.dist-info/LICENSE
iva_order_selection-0.0.2.dist-info/METADATA
iva_order_selection-0.0.2.dist-info/WHEEL
iva_order_selection-0.0.2.dist-info/top_level.txt
iva_order_selection-0.0.2.dist-info/RECORD
