Metadata-Version: 2.1
Name: iva-order-selection
Version: 0.0.2
Summary: Implementation of CMI-IVA
Home-page: https://mlsp.umbc.edu/Siddique
Author: M. A. B. S. Akhonda
Author-email: akhondams@nih.gov
License: LICENSE
Keywords: iva,model order selection,multiset analysis,common and distinct
Platform: UNKNOWN
Classifier: Programming Language :: Python :: 3
Classifier: License :: OSI Approved :: MIT License
Classifier: Operating System :: OS Independent
Requires-Python: >=3.6
Requires-Dist: numpy
Requires-Dist: scipy
Requires-Dist: pytest
Requires-Dist: joblib
Requires-Dist: tqdm
Requires-Dist: matplotlib
